snekmer/__init__.py
snekmer/_version.py
snekmer/alphabet.py
snekmer/cli.py
snekmer/cluster.py
snekmer/io.py
snekmer/model.py
snekmer/plot.py
snekmer/report.py
snekmer/score.py
snekmer/utils.py
snekmer/vectorize.py
snekmer/rules/apply.smk
snekmer/rules/cluster.smk
snekmer/rules/evaluate.smk
snekmer/rules/kmerize.smk
snekmer/rules/learn.smk
snekmer/rules/model.smk
snekmer/rules/process.smk
snekmer/rules/search.smk
snekmer/scripts/cluster_cluster.py
snekmer/scripts/model_model.py
snekmer/scripts/model_score.py
snekmer/templates/cluster_template.html
snekmer/templates/model_template.html
snekmer/templates/search_template.html
snekmer-1.2.0.dist-info/LICENSE
snekmer-1.2.0.dist-info/METADATA
snekmer-1.2.0.dist-info/WHEEL
snekmer-1.2.0.dist-info/entry_points.txt
snekmer-1.2.0.dist-info/top_level.txt
snekmer-1.2.0.dist-info/RECORD
