Metadata-Version: 2.1
Name: snekmer
Version: 1.2.0
Summary: A computational pipeline enabling functional annotation using amino acid recoding.
Author: Pacific Northwest National Laboratory
Maintainer-email: Christine Chang <christine.chang@pnnl.gov>, Jason McDermott <jason.mcdermott@pnnl.gov>
License: BSD 3-Clause License
Project-URL: Homepage, https://github.com/PNNL-CompBio/Snekmer
Project-URL: Documentation, https://snekmer.readthedocs.io
Project-URL: Issues, https://github.com/PNNL-CompBio/Snekmer/issues
Classifier: Programming Language :: Python :: 3
Classifier: License :: OSI Approved :: BSD License
Classifier: Operating System :: OS Independent
Classifier: Topic :: Scientific/Engineering :: Bio-Informatics
Requires-Python: >=3.8
License-File: LICENSE
Requires-Dist: biopython
Requires-Dist: matplotlib
Requires-Dist: numpy ==1.22.3
Requires-Dist: numba >=0.56
Requires-Dist: pandas ==1.4.2
Requires-Dist: seaborn
Requires-Dist: scipy
Requires-Dist: scikit-learn
Requires-Dist: snakemake ==7.0
Requires-Dist: tabulate ==0.8.10
Requires-Dist: umap-learn
Requires-Dist: hdbscan
Requires-Dist: pyarrow
